rafnixg/__init__.py
rafnixg/__main__.py
rafnixg/blog_posts.py
rafnixg/hashnode.py
rafnixg/links.py
rafnixg/rafnixg.py
rafnixg/resume.py
rafnixg-1.8.0.dist-info/licenses/LICENSE
rafnixg-1.8.0.dist-info/METADATA
rafnixg-1.8.0.dist-info/WHEEL
rafnixg-1.8.0.dist-info/entry_points.txt
rafnixg-1.8.0.dist-info/top_level.txt
rafnixg-1.8.0.dist-info/RECORD
