Metadata-Version: 2.4
Name: rafnixg
Version: 1.8.0
Summary: Rafnix Guzman Personal Card
Author-email: Rafnix Guzman <rafnixg@gmail.com>
License: MIT License
Project-URL: Homepage, https://github.com/rafnixg/rafnixg-lib
Keywords: personal card,console
Classifier: License :: OSI Approved :: MIT License
Classifier: Programming Language :: Python
Classifier: Programming Language :: Python :: 3
Requires-Python: >=3.9
License-File: LICENSE
Requires-Dist: rich
Requires-Dist: requests
Provides-Extra: dev
Requires-Dist: black; extra == "dev"
Requires-Dist: bumpver; extra == "dev"
Requires-Dist: isort; extra == "dev"
Requires-Dist: pip-tools; extra == "dev"
Requires-Dist: pytest; extra == "dev"
Dynamic: license-file
